dorfperfekt/__main__.py
dorfperfekt/display.py
dorfperfekt/tile.py
dorfperfekt/tilemap.py
dorfperfekt-0.2.3.dist-info/entry_points.txt
dorfperfekt-0.2.3.dist-info/LICENSE.md
dorfperfekt-0.2.3.dist-info/METADATA
dorfperfekt-0.2.3.dist-info/WHEEL
dorfperfekt-0.2.3.dist-info/RECORD
