Metadata-Version: 2.1
Name: dorfperfekt
Version: 0.2.3
Summary: Tile placement suggestions for the game Dorfromantik.
Home-page: https://github.com/amosborne/dorfperfekt
License: MIT
Author: amosborne
Author-email: amosborne@users.noreply.github.com
Requires-Python: >=3.9,<3.12
Classifier: License :: OSI Approved :: MIT License
Classifier: Programming Language :: Python :: 3
Classifier: Programming Language :: Python :: 3.9
Classifier: Programming Language :: Python :: 3.10
Classifier: Programming Language :: Python :: 3.11
Requires-Dist: PySide6 (>=6.2.3,<7.0.0)
Requires-Dist: aenum (>=3.1.8,<4.0.0)
Requires-Dist: cachetools (>=5.0.0,<6.0.0)
Requires-Dist: matplotlib (>=3.5.1,<4.0.0)
Requires-Dist: numpy (>=1.22.2,<2.0.0)
Project-URL: Repository, https://github.com/amosborne/dorfperfekt
